thanosql/__init__.py
thanosql/_base_client.py
thanosql/_client.py
thanosql/_error.py
thanosql/_service.py
thanosql/_util.py
thanosql/_version.py
thanosql/magic/__init__.py
thanosql/magic/exception.py
thanosql/magic/magic.py
thanosql/magic/parse.py
thanosql/magic/util.py
thanosql/resources/__init__.py
thanosql/resources/_file.py
thanosql/resources/_model.py
thanosql/resources/_query.py
thanosql/resources/_record.py
thanosql/resources/_schema.py
thanosql/resources/_table.py
thanosql/resources/_view.py
thanosql-1.0.11.dist-info/LICENSE
thanosql-1.0.11.dist-info/METADATA
thanosql-1.0.11.dist-info/WHEEL
thanosql-1.0.11.dist-info/top_level.txt
thanosql-1.0.11.dist-info/RECORD
