Metadata-Version: 2.1
Name: thanosql
Version: 1.0.11
Summary: ThanoSQL SDK for Python
Home-page: https://github.com/smartmind-team/thanosql-python
Author: SmartMind
Author-email: dev@smartmind.team
License: MIT
Keywords: smartmind thanosql sdk
Classifier: Intended Audience :: Developers
Classifier: Programming Language :: Python :: 3
Classifier: License :: OSI Approved :: MIT License
Classifier: Operating System :: OS Independent
Requires-Python: >= 3.8
License-File: LICENSE
Requires-Dist: jinja2
Requires-Dist: numpy
Requires-Dist: openpyxl
Requires-Dist: pandas
Requires-Dist: pydantic >=2.0
Requires-Dist: requests
Requires-Dist: tqdm
Requires-Dist: urllib3
Provides-Extra: dev
Requires-Dist: faker ; extra == 'dev'
Requires-Dist: pytest ; extra == 'dev'
Requires-Dist: myst-nb ; extra == 'dev'
Requires-Dist: sphinx-autoapi ; extra == 'dev'
Requires-Dist: sphinx-rtd-theme ; extra == 'dev'
Provides-Extra: magic
Requires-Dist: ipython ; extra == 'magic'
Requires-Dist: sqlalchemy ; extra == 'magic'
Requires-Dist: matplotlib ; extra == 'magic'
Requires-Dist: websocket-client ; extra == 'magic'
Requires-Dist: pglast ; extra == 'magic'
